hydra_plugins/hydra_optuna_sweeper/__init__.py
hydra_plugins/hydra_optuna_sweeper/_impl.py
hydra_plugins/hydra_optuna_sweeper/config.py
hydra_plugins/hydra_optuna_sweeper/optuna_sweeper.py
hydra_optuna_sweeper-1.2.0.dist-info/METADATA
hydra_optuna_sweeper-1.2.0.dist-info/WHEEL
hydra_optuna_sweeper-1.2.0.dist-info/top_level.txt
hydra_optuna_sweeper-1.2.0.dist-info/RECORD
