Metadata-Version: 2.1
Name: hydra-optuna-sweeper
Version: 1.2.0
Summary: Hydra Optuna Sweeper plugin
Home-page: https://github.com/facebookresearch/hydra/
Author: Toshihiko Yanase, Hiroyuki Vincent Yamazaki
Author-email: toshihiko.yanase@gmail.com, hiroyuki.vincent.yamazaki@gmail.com
License: UNKNOWN
Platform: UNKNOWN
Classifier: License :: OSI Approved :: MIT License
Classifier: Programming Language :: Python :: 3.6
Classifier: Programming Language :: Python :: 3.7
Classifier: Programming Language :: Python :: 3.8
Classifier: Programming Language :: Python :: 3.9
Classifier: Programming Language :: Python :: 3.10
Classifier: Operating System :: POSIX :: Linux
Classifier: Operating System :: MacOS
Classifier: Development Status :: 4 - Beta
Requires-Dist: hydra-core (>=1.1.0.dev7)
Requires-Dist: optuna (<3.0.0,>=2.10.0)
